mca.py
mca-1.0.4.dist-info/licenses/AUTHORS.rst
mca-1.0.4.dist-info/licenses/LICENSE
mca-1.0.4.dist-info/METADATA
mca-1.0.4.dist-info/WHEEL
mca-1.0.4.dist-info/top_level.txt
mca-1.0.4.dist-info/RECORD
